[
    {
        "id": "ec0251a4.82f6a",
        "type": "tab",
        "label": "Netio4All01-global",
        "disabled": false,
        "info": ""
    },
    {
        "id": "567685e6.ec2d8c",
        "type": "ibmiot in",
        "z": "ec0251a4.82f6a",
        "authentication": "boundService",
        "apiKey": "",
        "inputType": "evt",
        "logicalInterface": "",
        "ruleId": "",
        "deviceId": "01",
        "applicationId": "",
        "deviceType": "netio4all",
        "eventType": "voltage",
        "commandType": "",
        "format": "format_string",
        "name": "IBM IoT",
        "service": "registered",
        "allDevices": "",
        "allApplications": "",
        "allDeviceTypes": "",
        "allLogicalInterfaces": "",
        "allEvents": "",
        "allCommands": "",
        "allFormats": "",
        "qos": 0,
        "x": 120,
        "y": 100,
        "wires": [
            [
                "25f64c9c.4fda94",
                "d8932a62.1b68b8"
            ]
        ],
        "l": false
    },
    {
        "id": "25f64c9c.4fda94",
        "type": "debug",
        "z": "ec0251a4.82f6a",
        "name": "",
        "active": false,
        "tosidebar": true,
        "console": false,
        "tostatus": false,
        "complete": "true",
        "targetType": "full",
        "x": 240,
        "y": 60,
        "wires": [],
        "l": false
    },
    {
        "id": "b7011ffd.365ee",
        "type": "ui_gauge",
        "z": "ec0251a4.82f6a",
        "name": "",
        "group": "91281b5b.dac1e8",
        "order": 1,
        "width": 0,
        "height": 0,
        "gtype": "gage",
        "title": "Voltage",
        "label": "V",
        "format": "{{value | number:2}}",
        "min": "200",
        "max": "250",
        "colors": [
            "#00b500",
            "#e6e600",
            "#ca3838"
        ],
        "seg1": "",
        "seg2": "",
        "x": 420,
        "y": 120,
        "wires": [],
        "l": false
    },
    {
        "id": "d8932a62.1b68b8",
        "type": "function",
        "z": "ec0251a4.82f6a",
        "name": "",
        "func": "msg.payload=msg.payload/1000;\nreturn msg;",
        "outputs": 1,
        "noerr": 0,
        "x": 240,
        "y": 120,
        "wires": [
            [
                "b7011ffd.365ee",
                "e88c7054.c8d77"
            ]
        ],
        "l": false
    },
    {
        "id": "d749cf41.8ecaa",
        "type": "ibmiot in",
        "z": "ec0251a4.82f6a",
        "authentication": "boundService",
        "apiKey": "",
        "inputType": "evt",
        "logicalInterface": "",
        "ruleId": "",
        "deviceId": "01",
        "applicationId": "",
        "deviceType": "netio4all",
        "eventType": "frequency",
        "commandType": "",
        "format": "format_string",
        "name": "IBM IoT",
        "service": "registered",
        "allDevices": "",
        "allApplications": "",
        "allDeviceTypes": "",
        "allLogicalInterfaces": "",
        "allEvents": "",
        "allCommands": "",
        "allFormats": "",
        "qos": 0,
        "x": 115,
        "y": 240,
        "wires": [
            [
                "b041da32.d75888",
                "cd4bfdf.269c2"
            ]
        ],
        "l": false
    },
    {
        "id": "b041da32.d75888",
        "type": "debug",
        "z": "ec0251a4.82f6a",
        "name": "",
        "active": false,
        "tosidebar": true,
        "console": false,
        "tostatus": false,
        "complete": "true",
        "targetType": "full",
        "x": 235,
        "y": 200,
        "wires": [],
        "l": false
    },
    {
        "id": "538cac69.b588b4",
        "type": "ui_gauge",
        "z": "ec0251a4.82f6a",
        "name": "",
        "group": "91281b5b.dac1e8",
        "order": 4,
        "width": 0,
        "height": 0,
        "gtype": "gage",
        "title": "Frequency",
        "label": "Hz",
        "format": "{{value | number:2}}",
        "min": "45",
        "max": "55",
        "colors": [
            "#00b500",
            "#e6e600",
            "#ca3838"
        ],
        "seg1": "",
        "seg2": "",
        "x": 415,
        "y": 260,
        "wires": [],
        "l": false
    },
    {
        "id": "cd4bfdf.269c2",
        "type": "function",
        "z": "ec0251a4.82f6a",
        "name": "",
        "func": "msg.payload=msg.payload/1000;\nreturn msg;",
        "outputs": 1,
        "noerr": 0,
        "x": 235,
        "y": 260,
        "wires": [
            [
                "538cac69.b588b4",
                "9695f9c5.233378"
            ]
        ],
        "l": false
    },
    {
        "id": "e88c7054.c8d77",
        "type": "ui_chart",
        "z": "ec0251a4.82f6a",
        "name": "",
        "group": "91281b5b.dac1e8",
        "order": 2,
        "width": 0,
        "height": 0,
        "label": "Graph Voltage",
        "chartType": "line",
        "legend": "false",
        "xformat": "HH:mm:ss",
        "interpolate": "linear",
        "nodata": "",
        "dot": false,
        "ymin": "200",
        "ymax": "250",
        "removeOlder": 1,
        "removeOlderPoints": "",
        "removeOlderUnit": "3600",
        "cutout": 0,
        "useOneColor": false,
        "colors": [
            "#1f77b4",
            "#aec7e8",
            "#ff7f0e",
            "#2ca02c",
            "#98df8a",
            "#d62728",
            "#ff9896",
            "#9467bd",
            "#c5b0d5"
        ],
        "useOldStyle": false,
        "outputs": 1,
        "x": 415,
        "y": 160,
        "wires": [
            []
        ],
        "l": false
    },
    {
        "id": "9695f9c5.233378",
        "type": "ui_chart",
        "z": "ec0251a4.82f6a",
        "name": "",
        "group": "91281b5b.dac1e8",
        "order": 5,
        "width": 0,
        "height": 0,
        "label": "Graph Frequency",
        "chartType": "line",
        "legend": "false",
        "xformat": "HH:mm:ss",
        "interpolate": "linear",
        "nodata": "",
        "dot": false,
        "ymin": "45",
        "ymax": "55",
        "removeOlder": 1,
        "removeOlderPoints": "",
        "removeOlderUnit": "3600",
        "cutout": 0,
        "useOneColor": false,
        "colors": [
            "#1f77b4",
            "#aec7e8",
            "#ff7f0e",
            "#2ca02c",
            "#98df8a",
            "#d62728",
            "#ff9896",
            "#9467bd",
            "#c5b0d5"
        ],
        "useOldStyle": false,
        "outputs": 1,
        "x": 415,
        "y": 300,
        "wires": [
            []
        ],
        "l": false
    },
    {
        "id": "91281b5b.dac1e8",
        "type": "ui_group",
        "z": "",
        "name": "Netio4All01-global",
        "tab": "d0272ed3.61a1b",
        "disp": true,
        "width": "6",
        "collapse": false
    },
    {
        "id": "d0272ed3.61a1b",
        "type": "ui_tab",
        "z": "",
        "name": "Netio4All01",
        "icon": "dashboard",
        "order": 4,
        "disabled": false,
        "hidden": false
    }
]